sqla_vertica_python/__init__.py
sqla_vertica_python/vertica_python.py
sqlalchemy_vertica_python-0.6.3.dist-info/LICENSE
sqlalchemy_vertica_python-0.6.3.dist-info/METADATA
sqlalchemy_vertica_python-0.6.3.dist-info/WHEEL
sqlalchemy_vertica_python-0.6.3.dist-info/entry_points.txt
sqlalchemy_vertica_python-0.6.3.dist-info/top_level.txt
sqlalchemy_vertica_python-0.6.3.dist-info/RECORD
