Metadata-Version: 2.1
Name: sqlalchemy-vertica-python
Version: 0.6.3
Summary: Vertica dialect for sqlalchemy using vertica_python
Home-page: https://github.com/bluelabsio/sqlalchemy-vertica-python
Author: James Casbon, Luke Emery-Fertitta
Maintainer: Vince Broz
Maintainer-email: opensource@bluelabs.com
License: MIT
Download-URL: https://github.com/bluelabsio/sqlalchemy-vertica-python/tarball/0.6.3
Keywords: sqlalchemy,vertica,python
Platform: UNKNOWN
Classifier: Development Status :: 3 - Alpha
Classifier: License :: OSI Approved :: MIT License
Classifier: Programming Language :: Python :: 3.5
Classifier: Programming Language :: Python :: 3.6
Classifier: Programming Language :: Python :: 3.7
Classifier: Programming Language :: Python :: 3.8
Requires-Dist: vertica-python
